{
  "content_path": "docs",
  "domain": "docs",
  "fields": {
    "description": {
      "type": "text"
    },
    "features": {
      "items": {
        "fields": {
          "details": {
            "required": true,
            "type": "text"
          },
          "icon": {
            "type": "string"
          },
          "title": {
            "required": true,
            "type": "string"
          }
        },
        "type": "object"
      },
      "type": "array"
    },
    "hero": {
      "fields": {
        "actions": {
          "items": {
            "fields": {
              "link": {
                "required": true,
                "type": "string"
              },
              "text": {
                "required": true,
                "type": "string"
              },
              "theme": {
                "options": [
                  "brand",
                  "alt"
                ],
                "type": "select"
              }
            },
            "type": "object"
          },
          "type": "array"
        },
        "image": {
          "type": "image"
        },
        "name": {
          "type": "string"
        },
        "tagline": {
          "type": "text"
        },
        "text": {
          "type": "string"
        }
      },
      "type": "object"
    },
    "layout": {
      "options": [
        "doc",
        "home"
      ],
      "type": "select"
    },
    "order": {
      "type": "integer"
    },
    "sidebar_label": {
      "type": "string"
    },
    "slug": {
      "required": true,
      "type": "slug",
      "unique": true
    },
    "title": {
      "required": true,
      "type": "string"
    }
  },
  "i18n": false,
  "id": "docs-page",
  "kind": "document",
  "locale_strategy": "none"
}
